nksr/__init__.py
nksr-0.0.0.dist-info/METADATA
nksr-0.0.0.dist-info/WHEEL
nksr-0.0.0.dist-info/top_level.txt
nksr-0.0.0.dist-info/RECORD
