Metadata-Version: 2.1
Name: nksr
Version: 0.0.0
Summary: Neural Kernel Surface Reconstruction
Author-email: huangjh.work@outlook.com
Keywords: nksr,3d,reconstruction
Requires-Python: >=3.7
